quantlib_st/__init__.py
quantlib_st/cli/__init__.py
quantlib_st/cli/__main__.py
quantlib_st/cli/corr_cmd.py
quantlib_st/cli/costs_cmd.py
quantlib_st/cli/main.py
quantlib_st/core/__init__.py
quantlib_st/core/dateutils.py
quantlib_st/core/pandas/__init__.py
quantlib_st/core/pandas/frequency.py
quantlib_st/correlation/__init__.py
quantlib_st/correlation/correlation_over_time.py
quantlib_st/correlation/exponential_correlation.py
quantlib_st/correlation/fitting_dates.py
quantlib_st/costs/__init__.py
quantlib_st/costs/calculator.py
quantlib_st/costs/config.py
quantlib_st/costs/data_source.py
quantlib_st/estimators/__init__.py
quantlib_st/estimators/vol.py
quantlib_st-1.4.0.dist-info/licenses/LICENSE
tests/__init__.py
tests/correlation/__init__.py
tests/correlation/test_correlation.py
tests/correlation/test_correlationlist_as.py
tests/correlation/test_fitting_dates.py
tests/correlation/test_jsonable_to_long.py
tests/estimators/test_vol.py
quantlib_st-1.4.0.dist-info/METADATA
quantlib_st-1.4.0.dist-info/WHEEL
quantlib_st-1.4.0.dist-info/entry_points.txt
quantlib_st-1.4.0.dist-info/top_level.txt
quantlib_st-1.4.0.dist-info/RECORD
