Metadata-Version: 2.4
Name: quantlib-st
Version: 1.4.0
Summary: A quantitative finance library and cli for systematic trading
Author-email: Rodion Lim <rodion.lim@gmail.com>
Project-URL: Homepage, https://github.com/rodionlim/quantlib-st
Project-URL: Issues, https://github.com/rodionlim/quantlib-st/issues
Classifier: Programming Language :: Python :: 3
Classifier: License :: OSI Approved :: MIT License
Classifier: Operating System :: OS Independent
Requires-Python: >=3.11
License-File: LICENSE
Requires-Dist: numpy>=2.4.0
Requires-Dist: pandas>=2.3.3
Provides-Extra: dev
Requires-Dist: pip>=25.3; extra == "dev"
Requires-Dist: pytest>=9.0.2; extra == "dev"
Requires-Dist: pyinstaller>=6.17.0; extra == "dev"
Requires-Dist: twine>=6.2.0; extra == "dev"
Dynamic: license-file
